LICENSE
MANIFEST.in
README
setup.cfg
setup.py
rtorrent_notify.egg-info/PKG-INFO
rtorrent_notify.egg-info/SOURCES.txt
rtorrent_notify.egg-info/dependency_links.txt
rtorrent_notify.egg-info/entry_points.txt
rtorrent_notify.egg-info/requires.txt
rtorrent_notify.egg-info/top_level.txt
rtorrentnotify/__init__.py
rtorrentnotify/__main__.py
rtorrentnotify/test.py