Metadata-Version: 1.1
Name: rtorrent-notify
Version: 1.1.0
Summary: Notify of rtorrent events, through RSS or IRC (using Irker)
Home-page: http://git.p.engu.in/laurentb/rtorrent-notify/
Author: Laurent Bachelier
Author-email: laurent@bachelier.name
License: UNKNOWN
Platform: UNKNOWN
Classifier: Environment :: Console
Classifier: License :: OSI Approved :: MIT License
Classifier: Operating System :: POSIX
Classifier: Programming Language :: Python :: 2.6
Classifier: Programming Language :: Python :: 2.7
Classifier: Topic :: Internet
